Workbook

Sheet Test Report
A1: redBus MOBILE APPLICATION - FUNCTIONAL TEST REPORT
A2: Application: redBus (Mobile App / Mobile Web) | Scope: Login → Search → Seat → Payment → Ticket → Cancellation → Profile | Environment: QA | Prepared by: QA Team | EXECUTION STATUS: NOT EXECUTED – the "ITERATION 1: ACTUAL RESULT" column must be filled in by the tester during the actual run.
A3: S.NO | B3: MODULE | C3: SUB MODULE | D3: SUB MODULE 2 | E3: FUTURE NO | F3: TAB/PAGE | G3: FIELDS | H3: FUTURES DESCRIPTION | I3: TEST CASE NO | J3: STEPS TO FOLLOW FOR TESTING | K3: EXPECTED RESULT | L3: TEST DATA | M3: BROWSR | N3: ITERATION 1: ACTUAL RESULT
A4: 1 | B4: Authentication | C4: App Launch | D4: Splash Screen | E4: F-001 | F4: Splash / Landing | G4: App icon, Splash logo, Sign-in link | H4: Verify the redBus mobile app launches and lands on the Home / Sign-in screen. | I4: TC_LNH_001 | J4: 1. Unlock the mobile device. 2. Tap the redBus app icon. 3. Observe the splash screen. 4. Wait for the landing screen to load. | K4: App launches within 5 seconds, the splash logo is displayed and the Home screen with the "Sign In" option is shown without a crash. | L4: App: redBus v22.x Device: Pixel 7, Android 14 | M4: redBus Android App v22.x / Android 14 | N4: Not Executed
A5: 2 | B5: Authentication | C5: App Launch | D5: Runtime Permissions | E5: F-001 | F5: Permission Pop-up | G5: Allow / Deny (Location, Notification) | H5: Verify runtime permission prompts are shown on first launch and the app still works after Deny. | I5: TC_LNH_002 | J5: 1. Freshly install the app. 2. Launch the app. 3. Observe the Location and Notification permission pop-ups. 4. Tap "Deny" on both. 5. Continue to the Home screen. | K5: Permission pop-ups appear on first launch only. On Deny the app does not crash and the Home screen loads with manual city entry available. | L5: Fresh install, no cached data | M5: redBus Android App v22.x / Android 14 | N5: Not Executed
A6: 3 | B6: Authentication | C6: App Launch | D6: Navigation to Login | E6: F-002 | F6: Home > Account | G6: Account icon, Sign In button | H6: Verify the user can navigate from the Home screen to the Login screen. | I6: TC_LNH_003 | J6: 1. Launch the app. 2. Tap the "Account" icon in the bottom navigation bar. 3. Tap the "Sign In / Sign Up" button. | K6: The Login screen is displayed with the Mobile Number field, the country-code selector and the "Continue" button. | L6: Guest (not logged-in) user | M6: redBus Android App v22.x / Android 14 | N6: Not Executed
A7: 4 | B7: Authentication | C7: Login | D7: UI Validation | E7: F-003 | F7: Login Page | G7: Country code, Mobile Number, Continue, T&C link | H7: Verify all UI elements on the Login page are displayed correctly on a mobile viewport. | I7: TC_LGN_001 | J7: 1. Open the Login page. 2. Verify that the redBus logo, page title, country-code dropdown, Mobile Number field, "Continue" button, Terms & Conditions link and alternate login options are visible. 3. Rotate the device to landscape. | K7: All elements are visible, correctly aligned and not truncated, and the layout adjusts correctly in both portrait and landscape. | L7: N/A | M7: Chrome 126 / Android 14 (Pixel 7) | N7: Not Executed
A8: 5 | B8: Authentication | C8: Login | D8: Mobile Number - Field Validation | E8: F-003 | F8: Login Page | G8: Mobile Number | H8: Verify the Mobile Number field accepts numeric input only. | I8: TC_LGN_002 | J8: 1. Open the Login page. 2. Tap the Mobile Number field. 3. Verify that the numeric keypad opens. 4. Try to enter alphabets and special characters. | K8: The numeric keypad opens by default and alphabets / special characters are not accepted in the Mobile Number field. | L8: abcde , @#$%^ | M8: Chrome 126 / Android 14 (Pixel 7) | N8: Not Executed
A9: 6 | B9: Authentication | C9: Login | D9: Mobile Number - Boundary Value | E9: F-003 | F9: Login Page | G9: Mobile Number, Continue | H9: Verify validation for a mobile number with less than 10 digits. | I9: TC_LGN_003 | J9: 1. Open the Login page. 2. Enter a 9-digit mobile number. 3. Tap "Continue". | K9: The error message "Please enter a valid 10 digit mobile number" is displayed and no OTP is sent. | L9: 987654321 (9 digits) | M9: Chrome 126 / Android 14 (Pixel 7) | N9: Not Executed
A10: 7 | B10: Authentication | C10: Login | D10: Mobile Number - Boundary Value | E10: F-003 | F10: Login Page | G10: Mobile Number | H10: Verify the field does not accept more than 10 digits. | I10: TC_LGN_004 | J10: 1. Open the Login page. 2. Try to enter an 11-digit mobile number. 3. Observe the field content. | K10: The field restricts input to a maximum of 10 digits; the 11th digit is not accepted. | L10: 98765432101 (11 digits) | M10: Chrome 126 / Android 14 (Pixel 7) | N10: Not Executed
A11: 8 | B11: Authentication | C11: Login | D11: Mobile Number - Negative | E11: F-003 | F11: Login Page | G11: Mobile Number, Continue | H11: Verify validation when the Mobile Number field is left blank. | I11: TC_LGN_005 | J11: 1. Open the Login page. 2. Leave the Mobile Number field blank. 3. Tap "Continue". | K11: The error message "Please enter your mobile number" is displayed and the user remains on the Login page. | L11: Blank | M11: Chrome 126 / Android 14 (Pixel 7) | N11: Not Executed
A12: 9 | B12: Authentication | C12: Login | D12: Mobile Number - Negative | E12: F-003 | F12: Login Page | G12: Mobile Number, Continue | H12: Verify validation for an invalid number starting with 0. | I12: TC_LGN_006 | J12: 1. Open the Login page. 2. Enter a 10-digit number starting with 0. 3. Tap "Continue". | K12: The error message "Please enter a valid mobile number" is displayed and no OTP is triggered. | L12: 0123456789 | M12: Chrome 126 / Android 14 (Pixel 7) | N12: Not Executed
A13: 10 | B13: Authentication | C13: Login | D13: Country Code - Positive | E13: F-004 | F13: Login Page | G13: Country code dropdown, Mobile Number | H13: Verify the user can change the country code and log in with an international number. | I13: TC_LGN_007 | J13: 1. Open the Login page. 2. Tap the country-code dropdown. 3. Search for and select "Singapore (+65)". 4. Enter a valid Singapore mobile number. 5. Tap "Continue". | K13: The country code changes to +65, the digit-length validation updates to 8 digits and the OTP is sent to the international number. | L13: +65 81234567 | M13: Chrome 126 / Android 14 (Pixel 7) | N13: Not Executed
A14: 11 | B14: Authentication | C14: Login | D14: Mobile Number - Positive | E14: F-003 | F14: Login Page | G14: Mobile Number, Continue | H14: Verify the OTP is triggered for a valid registered mobile number. | I14: TC_LGN_008 | J14: 1. Open the Login page. 2. Enter a valid 10-digit registered mobile number. 3. Tap "Continue". | K14: The OTP Verification screen is displayed with the message "OTP sent to +91-98XXXXXX10" and an SMS containing the OTP is received. | L14: 9876543210 (registered) | M14: Chrome 126 / Android 14 (Pixel 7) | N14: Not Executed
A15: 12 | B15: Authentication | C15: Sign Up | D15: New User - Positive | E15: F-005 | F15: Login Page > Profile | G15: Mobile Number, Name, Email | H15: Verify a new (unregistered) mobile number is routed to the Sign-Up flow. | I15: TC_LGN_009 | J15: 1. Open the Login page. 2. Enter a valid unregistered 10-digit mobile number. 3. Tap "Continue". 4. Enter the received OTP. | K15: The OTP screen is shown and after verification the user is taken to the "Complete your profile" screen to enter Name and Email. | L15: 9000000001 (new number) | M15: Chrome 126 / Android 14 (Pixel 7) | N15: Not Executed
... A67: 64 | B67: Non-Functional | C67: Security | D67: Session Handling | E67: F-033 | F67: Account / My Bookings | G67: Session token, Cached data | H67: Verify protected pages cannot be accessed after logout. | I67: TC_NFR_006 | J67: 1. Log in and open My Bookings. 2. Log out. 3. Press the back button and re-open the My Bookings deep link. | K67: The user is redirected to the Login screen, cached booking data is not displayed and the previous session token is invalidated. | L67: Registered user | M67: redBus Android App v22.x / Android 14 | N67: Not Executed

Sheet Summary
A1: TEST EXECUTION SUMMARY - ITERATION 1
A3: MODULE | B3: TOTAL TEST CASES | C3: ITERATION 1 RESULT
A4: Authentication | B4: =COUNTIF('Test Report'!B4:B67,"Authentication") | C4: =COUNTIFS('Test Report'!B4:B67,"Authentication",'Test Report'!N4:N67,"Pass")&" Pass / "&COUNTIFS('Test Report'!B4:B67,"Authentication",'Test Report'!N4:N67,"Fail")&" Fail"
A5: Bus Booking | B5: =COUNTIF('Test Report'!B4:B67,"Bus Booking") | C5: =COUNTIFS('Test Report'!B4:B67,"Bus Booking",'Test Report'!N4:N67,"Pass")&" Pass / "&COUNTIFS('Test Report'!B4:B67,"Bus Booking",'Test Report'!N4:N67,"Fail")&" Fail"
A6: Payment | B6: =COUNTIF('Test Report'!B4:B67,"Payment") | C6: =COUNTIFS('Test Report'!B4:B67,"Payment",'Test Report'!N4:N67,"Pass")&" Pass / "&COUNTIFS('Test Report'!B4:B67,"Payment",'Test Report'!N4:N67,"Fail")&" Fail"
A7: Booking | B7: =COUNTIF('Test Report'!B4:B67,"Booking") | C7: =COUNTIFS('Test Report'!B4:B67,"Booking",'Test Report'!N4:N67,"Pass")&" Pass / "&COUNTIFS('Test Report'!B4:B67,"Booking",'Test Report'!N4:N67,"Fail")&" Fail"
A8: My Bookings | B8: =COUNTIF('Test Report'!B4:B67,"My Bookings") | C8: =COUNTIFS('Test Report'!B4:B67,"My Bookings",'Test Report'!N4:N67,"Pass")&" Pass / "&COUNTIFS('Test Report'!B4:B67,"My Bookings",'Test Report'!N4:N67,"Fail")&" Fail"
A9: Profile | B9: =COUNTIF('Test Report'!B4:B67,"Profile") | C9: =COUNTIFS('Test Report'!B4:B67,"Profile",'Test Report'!N4:N67,"Pass")&" Pass / "&COUNTIFS('Test Report'!B4:B67,"Profile",'Test Report'!N4:N67,"Fail")&" Fail"
A10: Non-Functional | B10: =COUNTIF('Test Report'!B4:B67,"Non-Functional") | C10: =COUNTIFS('Test Report'!B4:B67,"Non-Functional",'Test Report'!N4:N67,"Pass")&" Pass / "&COUNTIFS('Test Report'!B4:B67,"Non-Functional",'Test Report'!N4:N67,"Fail")&" Fail"
A11: TOTAL | B11: =SUM(B4:B10)
A13: STATUS | B13: COUNT | C13: % OF TOTAL
A14: Pass | B14: =COUNTIF('Test Report'!N4:N67,"Pass") | C14: =TEXT(COUNTIF('Test Report'!N4:N67,"Pass")/64,"0.0%")
A15: Fail | B15: =COUNTIF('Test Report'!N4:N67,"Fail") | C15: =TEXT(COUNTIF('Test Report'!N4:N67,"Fail")/64,"0.0%")
A16: Blocked | B16: =COUNTIF('Test Report'!N4:N67,"Blocked") | C16: =TEXT(COUNTIF('Test Report'!N4:N67,"Blocked")/64,"0.0%")
A17: Not Executed | B17: =COUNTIF('Test Report'!N4:N67,"Not Executed") | C17: =TEXT(COUNTIF('Test Report'!N4:N67,"Not Executed")/64,"0.0%")
A19: NOTE | B19: These test cases have NOT been executed. Every row in the "ITERATION 1: ACTUAL RESULT" column is pre-set to "Not Executed" and carries a Pass / Fail / Blocked / Not Executed dropdown for the tester to fill in during the real run. The counts above update automatically.
